edgefirst/schemas/__init__.py
edgefirst/schemas/builtin_interfaces.py
edgefirst/schemas/edgefirst_msgs.py
edgefirst/schemas/foxglove_msgs.py
edgefirst/schemas/geometry_msgs.py
edgefirst/schemas/nav_msgs.py
edgefirst/schemas/sensor_msgs.py
edgefirst/schemas/std_msgs.py
edgefirst_schemas-1.4.1.dist-info/licenses/LICENSE
edgefirst_schemas-1.4.1.dist-info/licenses/NOTICE
edgefirst_schemas-1.4.1.dist-info/METADATA
edgefirst_schemas-1.4.1.dist-info/WHEEL
edgefirst_schemas-1.4.1.dist-info/top_level.txt
edgefirst_schemas-1.4.1.dist-info/RECORD
