Metadata-Version: 2.4
Name: edgefirst-schemas
Version: 1.4.1
Summary: Message schemas for EdgeFirst Perception - ROS2 Common Interfaces, Foxglove, and custom types
Author-email: Au-Zone Technologies <support@au-zone.com>
License: 
Project-URL: Homepage, https://doc.edgefirst.ai
Project-URL: Documentation, https://doc.edgefirst.ai/latest/perception/
Project-URL: Repository, https://github.com/EdgeFirstAI/schemas
Project-URL: Issues, https://github.com/EdgeFirstAI/schemas/issues
Project-URL: Changelog, https://github.com/EdgeFirstAI/schemas/blob/main/CHANGELOG.md
Keywords: ros2,perception,schemas,edge-ai,zenoh,cdr,foxglove
Classifier: Development Status :: 4 - Beta
Classifier: Intended Audience :: Developers
Classifier: License :: OSI Approved :: Apache Software License
Classifier: Programming Language :: Python :: 3
Classifier: Programming Language :: Python :: 3.8
Classifier: Programming Language :: Python :: 3.9
Classifier: Programming Language :: Python :: 3.10
Classifier: Programming Language :: Python :: 3.11
Classifier: Programming Language :: Python :: 3.12
Classifier: Topic :: Software Development :: Libraries
Classifier: Topic :: Scientific/Engineering
Requires-Python: >=3.8
License-File: LICENSE
License-File: NOTICE
Requires-Dist: pycdr2
Dynamic: license-file
